HackRequests/HackRequests.py
HackRequests/__init__.py
HackRequests-1.2.dist-info/LICENSE
HackRequests-1.2.dist-info/METADATA
HackRequests-1.2.dist-info/WHEEL
HackRequests-1.2.dist-info/top_level.txt
HackRequests-1.2.dist-info/RECORD
