Metadata-Version: 2.1
Name: HackRequests
Version: 1.2
Summary: The hack-requests is an HTTP network library for hackers.
Home-page: https://github.com/boy-hack/hack-requests/
Author: w8ay
Author-email: w8ay@qq.com
License: MIT
Keywords: http requests hacker
Platform: UNKNOWN
